{
 "ID": "233",
 "NAME_CN": "黄金苹果",
 "NAME_JP": "黄金のリンゴ",
 "NAME": "",
 "HEAD1": "233C.png",
 "PIC1": "233A.png",
 "PIC2": "233B.png",
 "Avatar": "233",
 "STAR": "4",
 "LV1_HP": "100",
 "LV1_ATK": "100",
 "LVMAX_HP": "100",
 "LVMAX_ATK": "100",
 "COST": "9",
 "ILLUST": "——",
 "CV": "——",
 "ICO": "304.png",
 "SKILL_E": "只有阿塔兰忒(Archer)装备时，自身在场期间，己方全体的Quick卡性能提升15%",
 "SKILLMAX_E": "——",
 "INTRO": "——那是神明才能享受的果实。它能使人类的理性荡然无存，是拥有不死的功效的禁断的果实。\n\n只要使用这个，无论怎样的人都会停止脚步。对着这颗果实伸出手，想要吃它。就像是手碰到了烫的东西一定会缩手一样，这是刻印在身体上的条件反射。\n\n曾经有人使用这个，使我停下了脚步。在竞走的途中让我忘却了自我，停了下来。至于之后的事情，我不愿想起。\n\n所以这个就由我保管。不交给你。\n…因为，你并不需要这颗果实。\n是这样的吧？\n"
}