{
 "ID": "353",
 "NAME_CN": "向没有阳光的此处",
 "NAME_JP": "陽の差さぬ此処へ",
 "NAME": "",
 "HEAD1": "353C.png",
 "PIC1": "353A.png",
 "PIC2": "353B.png",
 "Avatar": "353",
 "STAR": "4",
 "LV1_HP": "100",
 "LV1_ATK": "100",
 "LVMAX_HP": "100",
 "LVMAX_ATK": "100",
 "COST": "9",
 "ILLUST": "---",
 "CV": "--",
 "ICO": "314.png",
 "SKILL_E": "只有卫宫(Assassin)装备时，自身在场期间，己方全体的Quick卡性能提升10% & Arts卡性能提升10%",
 "SKILLMAX_E": "--",
 "INTRO": "—————有个东西叫起源。\n\n不是什么难懂的事，就是字面上的意思。\n从什么开始的。\n从什么诞生的。\n母亲？不对。\n不是作为个人的那个，而是作为存在的那个。\n\n有人从「剑」中诞生。\n或许也有人从「无价值」中诞生吧。\n\n我的起源？\n你不是已经看到了吗。——切断，连结。\n虽然也用作通常的攻击，但确是我的第二宝具。\n神秘碾断（Fantasm Punishment）\n「切断」与「结合」的体现。\n是将我的起源化作有型的存在。"
}