{
 "ID": "570",
 "NAME_CN": "那时盛夏",
 "NAME_JP": "いつかの夏",
 "NAME": "",
 "HEAD1": "570C.png",
 "PIC1": "570A.png",
 "PIC2": "570B.png",
 "Avatar": "570",
 "STAR": "5",
 "LV1_HP": "750",
 "LV1_ATK": "0",
 "LVMAX_HP": "3000",
 "LVMAX_ATK": "0",
 "COST": "12",
 "ILLUST": "たけのこ星人",
 "CV": "——",
 "ICO": "304.png",
 "SKILL_E": "自身的Quick卡性能提升8% & 宝具威力提升8% & 在NP值为30%的状态下开始战斗",
 "SKILLMAX_E": "自身的Quick卡性能提升10% & 宝具威力提升10% & 在NP值为50%的状态下开始战斗[最大解放]",
 "INTRO": "日光灼灼，耀人眼目。\n在波光粼粼的水池里——\n\n「从导演那里借到游泳池的钥匙啦！\n稍微休息一下吧，前辈！」\n\n就像落入水中会破碎的泡沫一般，\n这是只存于记忆之中的，业已远去夏日。"
}