{
 "ID": "787",
 "NAME_CN": "ＯＴＭＡ",
 "NAME_JP": "ＯＴＭＡ",
 "NAME": "",
 "HEAD1": "787C.png",
 "PIC1": "787A.png",
 "PIC2": "787B.png",
 "Avatar": "787",
 "STAR": "4",
 "LV1_HP": "100",
 "LV1_ATK": "100",
 "LVMAX_HP": "100",
 "LVMAX_ATK": "100",
 "COST": "9",
 "ILLUST": "サクマミツロ",
 "CV": "——",
 "ICO": "305.png",
 "SKILL_E": "只有阿纳斯塔西娅(Caster)装备时，自身在场期间，己方全体的Arts卡性能提升10% & 宝具威力提升10%",
 "SKILLMAX_E": "——",
 "INTRO": "奥丽加\n塔季扬娜\n玛丽亚\n阿纳斯塔西娅\n取名字的首字母组合在一起，便是ＯＴＭＡ。\n这是属于我们的，秘密之名。\n不管是结婚，生下孩子……不得不分道扬镳\n我们是姐妹的事实也永远不会改变。\n不要再争吵了。\n不要再真正地去互相憎恨了。\n然后，无论如何，为了让我们能够过上\n善良的人生，向主进行祈祷吧―――\n\n是的，没错。\n这一点并没有实现，\n没有实现。\n\n啊……但是，也有一个愿望实现了。\n至少我们死的时候，是在一起的。"
}