{
 "ID": "861",
 "NAME_CN": "风雅之致",
 "NAME_JP": "風雅たれ",
 "NAME": "",
 "HEAD1": "861C.png",
 "PIC1": "861A.png",
 "PIC2": "861B.png",
 "Avatar": "861",
 "STAR": "5",
 "LV1_HP": "750",
 "LV1_ATK": "0",
 "LVMAX_HP": "3000",
 "LVMAX_ATK": "0",
 "COST": "12",
 "ILLUST": "BLACK",
 "CV": null,
 "ICO": "202.png",
 "SKILL_E": "通关时所获得的魔术礼装EXP提升1%（支援时提升3%）",
 "SKILLMAX_E": "通关时所获得的魔术礼装EXP提升5%（支援时提升15%）[最大解放]",
 "INTRO": "Noblesse of Rouge。\n保持风雅是美男子的特权。\n\n　　　　　　　　　　　　　　　※画像以实物为准\n\n「但是不少照片照的都不好呢。\n　我其实更苗条的，而且Tool Ⅳ型也没有这么可爱。\n　嗯？你问Tool Ⅳ型是什么样的女仆？\n　唔，虽然我这么比喻你可能不懂，但你这有南丁格尔小姐在吧？\n  她大概就是那种感觉。」"
}